MofanShujuchuliJiaocheng2017510/README.md
MofanShujuchuliJiaocheng2017510/__init__.py
MofanShujuchuliJiaocheng2017510/__main__.py
MofanShujuchuliJiaocheng2017510/file.epub
MofanShujuchuliJiaocheng2017510/index.html
MofanShujuchuliJiaocheng2017510/css/__init__.py
MofanShujuchuliJiaocheng2017510/css/annotations.css
MofanShujuchuliJiaocheng2017510/css/main.css
MofanShujuchuliJiaocheng2017510/css/normalize.css
MofanShujuchuliJiaocheng2017510/css/popup.css
MofanShujuchuliJiaocheng2017510/font/__init__.py
MofanShujuchuliJiaocheng2017510/font/fontello.eot
MofanShujuchuliJiaocheng2017510/font/fontello.svg
MofanShujuchuliJiaocheng2017510/font/fontello.ttf
MofanShujuchuliJiaocheng2017510/font/fontello.woff
MofanShujuchuliJiaocheng2017510/img/__init__.py
MofanShujuchuliJiaocheng2017510/img/annotator-glyph-sprite.png
MofanShujuchuliJiaocheng2017510/img/annotator-icon-sprite.png
MofanShujuchuliJiaocheng2017510/img/apple-touch-icon.png
MofanShujuchuliJiaocheng2017510/img/cancelfullscreen.png
MofanShujuchuliJiaocheng2017510/img/close.png
MofanShujuchuliJiaocheng2017510/img/fullscreen.png
MofanShujuchuliJiaocheng2017510/img/loader.gif
MofanShujuchuliJiaocheng2017510/img/menu-icon.png
MofanShujuchuliJiaocheng2017510/img/save.png
MofanShujuchuliJiaocheng2017510/img/saved.png
MofanShujuchuliJiaocheng2017510/img/settings-s.png
MofanShujuchuliJiaocheng2017510/img/settings.png
MofanShujuchuliJiaocheng2017510/img/star.png
MofanShujuchuliJiaocheng2017510/js/__init__.py
MofanShujuchuliJiaocheng2017510/js/epub.js
MofanShujuchuliJiaocheng2017510/js/epub.min.js
MofanShujuchuliJiaocheng2017510/js/epub.min.map
MofanShujuchuliJiaocheng2017510/js/hooks.min.js
MofanShujuchuliJiaocheng2017510/js/hooks.min.map
MofanShujuchuliJiaocheng2017510/js/reader.js
MofanShujuchuliJiaocheng2017510/js/reader.js.map
MofanShujuchuliJiaocheng2017510/js/reader.min.js
MofanShujuchuliJiaocheng2017510/js/reader.min.map
MofanShujuchuliJiaocheng2017510/js/hooks/__init__.py
mofan_shujuchuli_jiaocheng_2017_5_10-2024.3.2.0.dist-info/METADATA
mofan_shujuchuli_jiaocheng_2017_5_10-2024.3.2.0.dist-info/WHEEL
mofan_shujuchuli_jiaocheng_2017_5_10-2024.3.2.0.dist-info/entry_points.txt
mofan_shujuchuli_jiaocheng_2017_5_10-2024.3.2.0.dist-info/top_level.txt
mofan_shujuchuli_jiaocheng_2017_5_10-2024.3.2.0.dist-info/RECORD
